azurecr_browser/__init__.py
azurecr_browser/app.py
azurecr_browser/ask.py
azurecr_browser/azure.py
azurecr_browser/config.py
azurecr_browser/docker.py
azurecr_browser/renderables/__init__.py
azurecr_browser/renderables/help.py
azurecr_browser/renderables/paginated_table.py
azurecr_browser/renderables/repos_table.py
azurecr_browser/renderables/tag_properties.py
azurecr_browser/renderables/tags_table.py
azurecr_browser/styles.py
azurecr_browser/util.py
azurecr_browser/widgets/__init__.py
azurecr_browser/widgets/flash.py
azurecr_browser/widgets/header.py
azurecr_browser/widgets/help.py
azurecr_browser/widgets/repos.py
azurecr_browser/widgets/search.py
azurecr_browser/widgets/tag_properties.py
azurecr_browser/widgets/tags.py
azurecr_browser-1.0.1.dist-info/entry_points.txt
azurecr_browser-1.0.1.dist-info/LICENSE
azurecr_browser-1.0.1.dist-info/WHEEL
azurecr_browser-1.0.1.dist-info/METADATA
azurecr_browser-1.0.1.dist-info/RECORD
