Metadata-Version: 2.1
Name: azurecr-browser
Version: 1.0.1
Summary: A terminal user interface for managing artifacts in Azure Container Registry
License: MIT
Author: Sam Dobson
Author-email: 1309834+samdobson@users.noreply.github.com
Requires-Python: >=3.7,<4.0
Classifier: License :: OSI Approved :: MIT License
Classifier: Programming Language :: Python :: 3
Classifier: Programming Language :: Python :: 3.10
Classifier: Programming Language :: Python :: 3.7
Classifier: Programming Language :: Python :: 3.8
Classifier: Programming Language :: Python :: 3.9
Requires-Dist: aiodocker (>=0.21.0,<0.22.0)
Requires-Dist: aiohttp (>=3.8.1,<4.0.0)
Requires-Dist: azure-containerregistry (>=1.0.0b7,<2.0.0)
Requires-Dist: azure-identity (>=1.7.1,<2.0.0)
Requires-Dist: click (>=8.0.3,<9.0.0)
Requires-Dist: fast-autocomplete[pylev] (>=0.9.0,<0.10.0)
Requires-Dist: importlib-metadata (>=4.10.0,<5.0.0)
Requires-Dist: pyperclip (>=1.8.2,<2.0.0)
Requires-Dist: rich (>=10.11.0,<11.0.0)
Requires-Dist: textual (>=0.1.12,<0.2.0)
Requires-Dist: textual-inputs (>=0.2.0,<0.3.0)
Requires-Dist: toml (>=0.10.2,<0.11.0)
Requires-Dist: validators (>=0.18.2,<0.19.0)
